{"ticker": "NKR", "scrape_date": "2021-09-21", "scrape_url": "https://nekkar.com/ir/shareholders/", "shareholder_update": "2020-12-31", "shareholders ": [{"shareholder_name": "Skeie Technology AS", "number_of_shares": "26,568,237", "percent_of_total": "25.0"}, {"shareholder_name": "Rasmussengruppen AS", "number_of_shares": "11,512,506", "percent_of_total": "10.8"}, {"shareholder_name": "MP Pensjon PK", "number_of_shares": "5,880,713", "percent_of_total": "5.5"}, {"shareholder_name": "Tigerstaden AS", "number_of_shares": "5,526,634", "percent_of_total": "5.2"}, {"shareholder_name": "Skeie Capital Investment", "number_of_shares": "4,907,586", "percent_of_total": "4.6"}, {"shareholder_name": "Avanza Bank AB", "number_of_shares": "4,261,099", "percent_of_total": "4.0"}, {"shareholder_name": "Vinterstua AS", "number_of_shares": "4,672,200", "percent_of_total": "2.5"}, {"shareholder_name": "Fender Eiendom AS", "number_of_shares": "1,554,626", "percent_of_total": "1.5"}, {"shareholder_name": "Skeie Consultants AS", "number_of_shares": "1,507,243", "percent_of_total": "1.4"}, {"shareholder_name": "Morgan Stanley & Co. International", "number_of_shares": "1,483,824", "percent_of_total": "1.4"}, {"shareholder_name": "Itlution AS", "number_of_shares": "1,475,261", "percent_of_total": "1.4"}, {"shareholder_name": "Roger Sebastian Sedal", "number_of_shares": "1,460,000", "percent_of_total": "1.4"}, {"shareholder_name": "Tigerstaden Invest AS", "number_of_shares": "1,045,000", "percent_of_total": "1.4"}, {"shareholder_name": "Einar Pedersen", "number_of_shares": "1,000,000", "percent_of_total": "0.9"}, {"shareholder_name": "Pirol AS", "number_of_shares": "1,000,000", "percent_of_total": "0.9"}, {"shareholder_name": "Nawa Invest AS", "number_of_shares": "1,000,000", "percent_of_total": "0.9"}, {"shareholder_name": "Guttis AS", "number_of_shares": "1,000,000", "percent_of_total": "0.9"}, {"shareholder_name": "Tigergutt Invest AS", "number_of_shares": "999,981", "percent_of_total": "0.9"}, {"shareholder_name": "Sogna Capital AS", "number_of_shares": "871,507", "percent_of_total": "0.8"}, {"shareholder_name": "Skeie Alpha Equity AS", "number_of_shares": "804,828", "percent_of_total": "0.8"}, {"shareholder_name": "TOTAL, 20 largest", "number_of_shares": "77,759,271", "percent_of_total": "73.13"}], "stock_type": null, "error": null}