{"ticker": "OKEA", "scrape_date": "2021-09-21", "scrape_url": "https://www.okea.no/investor/share-information/", "shareholder_update": "", "shareholders ": [{"shareholder_name": "BCPR PTE. LTD.", "number_of_shares": "47,477,563", "% of Top 20": "55.65", "percent_of_total": "46.09", "Type": "COMP", "Country": "SGP"}, {"shareholder_name": "OKEA HOLDINGS LTD.", "number_of_shares": "19,072,993", "% of Top 20": "22.35", "percent_of_total": "18.52", "Type": "COMP", "Country": "BMU"}, {"shareholder_name": "CHURCH BAY TRUST CO. LTD", "number_of_shares": "6,113,079", "% of Top 20": "7.16", "percent_of_total": "5.93", "Type": "COMP", "Country": "BMU"}, {"shareholder_name": "SALT VALUE AS", "number_of_shares": "1,967,257", "% of Top 20": "2.31", "percent_of_total": "1.91", "Type": "COMP", "Country": "NOR"}, {"shareholder_name": "K\u00d8RVEN AS", "number_of_shares": "1,430,087", "% of Top 20": "1.68", "percent_of_total": "1.39", "Type": "COMP", "Country": "NOR"}, {"shareholder_name": "SJ\u00c6KERHATTEN AS", "number_of_shares": "1,412,537", "% of Top 20": "1.66", "percent_of_total": "1.37", "Type": "COMP", "Country": "NOR"}, {"shareholder_name": "SPAREBANK 1 SMN INVEST AS", "number_of_shares": "1,157,978", "% of Top 20": "1.36", "percent_of_total": "1.12", "Type": "COMP", "Country": "NOR"}, {"shareholder_name": "GH HOLDING AS", "number_of_shares": "1,115,379", "% of Top 20": "1.31", "percent_of_total": "1.08", "Type": "COMP", "Country": "NOR"}, {"shareholder_name": "JENSSEN & CO AS", "number_of_shares": "1,030,860", "% of Top 20": "1.21", "percent_of_total": "1.0", "Type": "COMP", "Country": "NOR"}, {"shareholder_name": "LIGNA AS", "number_of_shares": "675,640", "% of Top 20": "0.79", "percent_of_total": "0.66", "Type": "COMP", "Country": "NOR"}, {"shareholder_name": "BNP PARIBAS SECURITIES SERVICES", "number_of_shares": "600,000", "% of Top 20": "0.7", "percent_of_total": "0.58", "Type": "NOM", "Country": "LUX"}, {"shareholder_name": "SKJEFSTAD VESTRE AS", "number_of_shares": "582,730", "% of Top 20": "0.68", "percent_of_total": "0.57", "Type": "COMP", "Country": "NOR"}, {"shareholder_name": "B FINANS AS", "number_of_shares": "499,983", "% of Top 20": "0.59", "percent_of_total": "0.49", "Type": "COMP", "Country": "NOR"}, {"shareholder_name": "ESPEDAL & CO AS", "number_of_shares": "434,273", "% of Top 20": "0.51", "percent_of_total": "0.42", "Type": "COMP", "Country": "NOR"}, {"shareholder_name": "MUST INVEST AS", "number_of_shares": "366,296", "% of Top 20": "0.43", "percent_of_total": "0.36", "Type": "COMP", "Country": "NOR"}, {"shareholder_name": "JOHAN VINJE AS", "number_of_shares": "323,625", "% of Top 20": "0.38", "percent_of_total": "0.31", "Type": "COMP", "Country": "NOR"}, {"shareholder_name": "BERGEN KOMMUNALE PENSJONSKASSE", "number_of_shares": "308,600", "% of Top 20": "0.36", "percent_of_total": "0.3", "Type": "COMP", "Country": "NOR"}, {"shareholder_name": "BERNHD. BREKKE A/S", "number_of_shares": "253,370", "% of Top 20": "0.3", "percent_of_total": "0.25", "Type": "COMP", "Country": "NOR"}, {"shareholder_name": "TRIPPEL-L AS", "number_of_shares": "253,270", "% of Top 20": "0.3", "percent_of_total": "0.25", "Type": "COMP", "Country": "NOR"}, {"shareholder_name": "LYCKLIGA GATAN AS", "number_of_shares": "243,204", "% of Top 20": "0.29", "percent_of_total": "0.24", "Type": "COMP", "Country": "NOR"}], "stock_type": null, "error": null}