{"ticker": "TRVX", "scrape_date": "2021-09-21", "scrape_url": "https://www.targovax.com/en/largest-shareholders/", "shareholder_update": "2021-08-04", "shareholders ": [{"shareholder_name": "HealthCap", "number_of_shares": "12\u00a0405\u00a0584", "2": "0.29", "percent_of_total": "0.14", "4": "ORD", "5": "SWE"}, {"shareholder_name": "RADFORSK INVESTERINGSSTIFTELSE", "number_of_shares": "4\u00a0427\u00a0255", "2": "0.1", "percent_of_total": "0.05", "4": "ORD", "5": "NOR"}, {"shareholder_name": "FJARDE AP-FONDEN", "number_of_shares": "4\u00a0000\u00a0000", "2": "0.09", "percent_of_total": "0.05", "4": "ORD", "5": "SWE"}, {"shareholder_name": "Goldman Sachs International", "number_of_shares": "1\u00a0993\u00a0964", "2": "0.05", "percent_of_total": "0.02", "4": "NOM", "5": "GBR"}, {"shareholder_name": "THORENDAHL INVEST AS", "number_of_shares": "1\u00a0750\u00a0000", "2": "0.04", "percent_of_total": "0.02", "4": "ORD", "5": "NOR"}, {"shareholder_name": "VERDIPAPIRFONDET NORDEA KAPITAL", "number_of_shares": "1\u00a0748\u00a0448", "2": "0.04", "percent_of_total": "0.02", "4": "ORD", "5": "NOR"}, {"shareholder_name": "B\u00c6KKELAGET HOLDING AS", "number_of_shares": "1\u00a0718\u00a0190", "2": "0.04", "percent_of_total": "0.02", "4": "ORD", "5": "NOR"}, {"shareholder_name": "Nordnet Bank AB", "number_of_shares": "1\u00a0651\u00a0389", "2": "0.04", "percent_of_total": "0.02", "4": "NOM", "5": "SWE"}, {"shareholder_name": "VERDIPAPIRFONDET NORDEA AVKASTNING", "number_of_shares": "1\u00a0649\u00a0274", "2": "0.04", "percent_of_total": "0.02", "4": "ORD", "5": "NOR"}, {"shareholder_name": "Danske Bank A/S", "number_of_shares": "1\u00a0566\u00a0309", "2": "0.04", "percent_of_total": "0.02", "4": "NOM", "5": "DNK"}, {"shareholder_name": "NORDNET LIVSFORSIKRING AS", "number_of_shares": "1\u00a0352\u00a0085", "2": "0.03", "percent_of_total": "0.02", "4": "ORD", "5": "NOR"}, {"shareholder_name": "PETTERSEN", "number_of_shares": "1\u00a0265\u00a0797", "2": "0.03", "percent_of_total": "0.01", "4": "ORD", "5": "NOR"}, {"shareholder_name": "VERDIPAPIRFONDET NORDEA NORGE PLUS", "number_of_shares": "1\u00a0076\u00a0603", "2": "0.03", "percent_of_total": "0.01", "4": "ORD", "5": "NOR"}, {"shareholder_name": "MP PENSJON PK", "number_of_shares": "991\u00a0725", "2": "0.02", "percent_of_total": "0.01", "4": "ORD", "5": "NOR"}, {"shareholder_name": "Morgan Stanley & Co. International", "number_of_shares": "968\u00a0685", "2": "0.02", "percent_of_total": "0.01", "4": "ORD", "5": "GBR"}, {"shareholder_name": "The Bank of New York Mellon SA/NV", "number_of_shares": "932\u00a0682", "2": "0.02", "percent_of_total": "0.01", "4": "NOM", "5": "IRL"}, {"shareholder_name": "J.P. Morgan Bank Luxembourg S.A.", "number_of_shares": "820\u00a0000", "2": "0.02", "percent_of_total": "0.01", "4": "NOM", "5": "LUX"}, {"shareholder_name": "PRIETA AS", "number_of_shares": "720\u00a0000", "2": "0.02", "percent_of_total": "0.01", "4": "ORD", "5": "NOR"}, {"shareholder_name": "SIVILINGENI\u00d8R JON-ARILD ANDREASSEN", "number_of_shares": "625\u00a0160", "2": "0.01", "percent_of_total": "0.01", "4": "ORD", "5": "NOR"}, {"shareholder_name": "BRABO AS", "number_of_shares": "624\u00a0915", "2": "0.01", "percent_of_total": "0.01", "4": "ORD", "5": "NOR"}, {"shareholder_name": "Total number owned by top 20", "number_of_shares": "42\u00a0288\u00a0065", "2": "nan", "percent_of_total": "nan", "4": "nan", "5": "nan"}, {"shareholder_name": "Total number of shares", "number_of_shares": "86\u00a0582\u00a0405", "2": "nan", "percent_of_total": "nan", "4": "nan", "5": "nan"}], "stock_type": null, "error": null}